suicide_news_classifer_spanish/__init__.py
suicide_news_classifer_spanish/suicide_classifier.py
suicide_news_classifer_spanish/test_suicide_classifier.py
suicide_news_classifer_spanish/saved_model/model.h5
suicide_news_classifer_spanish/saved_model/model.json
suicide_news_classifer_spanish/saved_model/tokenizer.pickle
suicide_news_classifer_spanish-0.0.6.dist-info/LICENSE
suicide_news_classifer_spanish-0.0.6.dist-info/METADATA
suicide_news_classifer_spanish-0.0.6.dist-info/WHEEL
suicide_news_classifer_spanish-0.0.6.dist-info/top_level.txt
suicide_news_classifer_spanish-0.0.6.dist-info/RECORD
