Metadata-Version: 2.1
Name: suicide-news-classifer-spanish
Version: 0.0.6
Summary: A classifier for suicide newspaper news in spanish
Home-page: https://github.com/domestic-violence-ai-studies/domestic-violence-news-classifier-spanish
Author: Hugo J. Bello
Author-email: hjbello.wk@gmail.com
License: UNKNOWN
Platform: UNKNOWN
Classifier: Programming Language :: Python :: 3
Classifier: License :: OSI Approved :: MIT License
Classifier: Operating System :: OS Independent
